pyquebec/config.py
pyquebec/database.py
pyquebec/dbobjects.py
pyquebec/formatters.py
pyquebec/pyquebec.ini
pyquebec/pyquebec.py
pyquebec/querybuilder.py
pyquebec/schema_reader.py
pyquebec/__init__.py
pyquebec/resources/jquery-1.11.1.min.js
pyquebec/resources/jquery.dataTables.css
pyquebec/resources/jquery.dataTables.min.js
pyquebec-0.9.0.dist-info/DESCRIPTION.rst
pyquebec-0.9.0.dist-info/METADATA
pyquebec-0.9.0.dist-info/metadata.json
pyquebec-0.9.0.dist-info/RECORD
pyquebec-0.9.0.dist-info/top_level.txt
pyquebec-0.9.0.dist-info/WHEEL
