Metadata-Version: 2.0
Name: pyquebec
Version: 0.9.0
Summary: A Python package to create simple SQL queries from the console, and quickly display the returned information.
Home-page: https://github.com/sebasmonia/pyquebec
Author: Sebastián Monía
Author-email: smonia@outlook.com
License: MIT
Keywords: SQL development console MSSQL SQLite
Platform: UNKNOWN
Classifier: Programming Language :: Python
Classifier: Operating System :: OS Independent
Classifier: Development Status :: 3 - Alpha
Classifier: Environment :: Console
Classifier: Intended Audience :: Developers
Classifier: Intended Audience :: Information Technology
Classifier: Intended Audience :: System Administrators
Classifier: License :: OSI Approved :: MIT License
Classifier: Operating System :: Microsoft :: Windows
Classifier: Operating System :: OS Independent
Classifier: Programming Language :: SQL
Classifier: Topic :: Database
Classifier: Topic :: Software Development
Classifier: Topic :: Utilities
Requires-Dist: pypyodbc
Requires-Dist: tabulate
